[{"buyer":"Sprocket Corp","productId":2,"quantity":20,"shippingAddress":"123 Smith Street, County, Country.","shippingTarget":1527074580000},{"buyer":"Sprocket Corp","productId":40,"quantity":1,"shippingAddress":"123 Smith Street, County, Country.","shippingTarget":1527074580000},{"buyer":"Doohickey Inc","productId":3,"quantity":10,"shippingAddress":"404 Unknown Street, County, Country.","shippingTarget":1526815380000},{"buyer":"Doohickey Inc","productId":13,"quantity":5,"shippingAddress":"404 Unknown Street, County, Country.","shippingTarget":1526815380000},{"buyer":"Doohickey Inc","productId":12,"quantity":10,"shippingAddress":"404 Unknown Street, County, Country.","shippingTarget":1526815380000},{"buyer":"Doohickey Inc","productId":40,"quantity":4,"shippingAddress":"404 Unknown Street, County, Country.","shippingTarget":1526815380000},{"buyer":"Super Secret Corp","productId":1,"quantity":100,"shippingAddress":"520 Unknown Place, Mysterium, Secretania.","shippingTarget":1527834900000},{"buyer":"Super Secret Corp","productId":31,"quantity":5000,"shippingAddress":"520 Unknown Place, Mysterium, Secretania.","shippingTarget":1527834900000},{"buyer":"Sprocket Corp","productId":2,"quantity":1000999,"shippingAddress":"123 Smith Street, County, Country.","shippingTarget":1606321980000},{"buyer":"Sprocket Corp","productId":2,"quantity":1500,"shippingAddress":"123 Smith Street, County, Country.","shippingTarget":1606323960000},{"buyer":"Sprocket Corp","productId":2,"quantity":null,"shippingAddress":"123 Smith Street, County, Country.","shippingTarget":1606323960000},{"buyer":"Sprocket Corp","productId":2,"quantity":1500,"shippingAddress":"123 Smith Street, County, Country.","shippingTarget":1606324020000},{"buyer":"Sprocket Corp","productId":2,"quantity":null,"shippingAddress":"123 Smith Street, County, Country.","shippingTarget":1606324020000},{"buyer":"Sprocket Corp","productId":2,"quantity":1500,"shippingAddress":"123 Smith Street, County, Country.","shippingTarget":1606324080000},{"buyer":"Sprocket Corp","productId":2,"quantity":null,"shippingAddress":"123 Smith Street, County, Country.","shippingTarget":1606324080000},{"buyer":"Sprocket Corp","productId":40,"quantity":15,"shippingAddress":"123 Smith Street, County, Country.","shippingTarget":1606324080000},{"buyer":"Sprocket Corp","productId":2,"quantity":null,"shippingAddress":"123 Smith Street, County, Country.","shippingTarget":1606324080000},{"buyer":"Sprocket Corp","productId":30,"quantity":15,"shippingAddress":"123 Smith Street, County, Country.","shippingTarget":1606324080000},{"buyer":"Sprocket Corp","productId":2,"quantity":100,"shippingAddress":"123 Smith Street, County, Country.","shippingTarget":1606324080000},{"buyer":"Doohickey Inc","productId":13,"quantity":15,"shippingAddress":"404 Unknown Street, County, Country.","shippingTarget":1606324140000},{"buyer":"Doohickey Inc","productId":2,"quantity":100,"shippingAddress":"404 Unknown Street, County, Country.","shippingTarget":1606324140000}]